cocotbext/__init__.py
cocotbext/dyulib/__init__.py
cocotbext/dyulib/cli.py
cocotbext/dyulib/decorators.py
cocotbext/dyulib/dyutools.py
cocotbext/dyulib/fcov_merge.py
cocotbext/dyulib/filelib.py
cocotbext/dyulib/reset.py
cocotbext_dyulib-0.0.4.dist-info/METADATA
cocotbext_dyulib-0.0.4.dist-info/WHEEL
cocotbext_dyulib-0.0.4.dist-info/entry_points.txt
cocotbext_dyulib-0.0.4.dist-info/licenses/LICENSE
cocotbext_dyulib-0.0.4.dist-info/RECORD
