Metadata-Version: 2.1
Name: cocotbext-dyulib
Version: 0.0.4
Summary: Libraries, templates and tools for working with cocotb.
Author-Email: Vijayvithal Jahagirdar <jahagirdar.vs@gmail.com>
License: BSD-2-Clause
Classifier: Development Status :: 4 - Beta
Classifier: Intended Audience :: Developers
Classifier: Programming Language :: Python
Classifier: Programming Language :: Python :: 3
Classifier: Programming Language :: Python :: 3 :: Only
Classifier: Programming Language :: Python :: 3.8
Classifier: Programming Language :: Python :: 3.9
Classifier: Programming Language :: Python :: 3.10
Classifier: Programming Language :: Python :: 3.11
Classifier: Programming Language :: Python :: 3.12
Classifier: Topic :: Documentation
Classifier: Topic :: Software Development
Classifier: Topic :: Utilities
Classifier: Typing :: Typed
Project-URL: Homepage, https://jahagirdar.github.io/cocotbext-dyulib
Project-URL: Documentation, https://jahagirdar.github.io/cocotbext-dyulib
Project-URL: Changelog, https://jahagirdar.github.io/cocotbext-dyulib/changelog
Project-URL: Repository, https://github.com/jahagirdar/cocotbext-dyulib
Project-URL: Issues, https://github.com/jahagirdar/cocotbext-dyulib/issues
Project-URL: Discussions, https://github.com/jahagirdar/cocotbext-dyulib/discussions
Project-URL: Gitter, https://gitter.im/cocotbext-dyulib/community
Project-URL: Funding, https://github.com/sponsors/jahagirdar
Requires-Python: >=3.8
Requires-Dist: cocotb-coverage>=1.2.0
Requires-Dist: click>=8.1.7
Requires-Dist: editables>=0.5
